MANIFEST.in
setup.cfg
setup.py
tw2/__init__.py
tw2.lesscss.egg-info/PKG-INFO
tw2.lesscss.egg-info/SOURCES.txt
tw2.lesscss.egg-info/dependency_links.txt
tw2.lesscss.egg-info/entry_points.txt
tw2.lesscss.egg-info/namespace_packages.txt
tw2.lesscss.egg-info/not-zip-safe
tw2.lesscss.egg-info/paster_plugins.txt
tw2.lesscss.egg-info/requires.txt
tw2.lesscss.egg-info/top_level.txt
tw2/lesscss/__init__.py
tw2/lesscss/base.py
tw2/lesscss/resources.py
tw2/lesscss/samples.py
tw2/lesscss/version.py
tw2/lesscss/static/lesscss/1.2.2/less.min.js
tw2/lesscss/templates/__init__.py
tw2/lesscss/templates/lesslink.html
tw2/lesscss/templates/lesslink.mak