Metadata-Version: 1.0
Name: tw2.lesscss
Version: 2.0.1c
Summary: Less CSS support for ToscaWidgets 2
Home-page: https://github.com/toscawidgets/tw2.lesscss
Author: Greg Jurman
Author-email: gdj2214@rit.edu
License: UNKNOWN
Keywords: toscawidgets.widgets
Platform: UNKNOWN
Classifier: Development Status :: 3 - Alpha
Classifier: Environment :: Web Environment
Classifier: Environment :: Web Environment :: ToscaWidgets
Classifier: Topic :: Software Development :: Libraries :: Python Modules
Classifier: Topic :: Software Development :: Widget Sets
Classifier: Intended Audience :: Developers
Classifier: Operating System :: OS Independent
Classifier: Programming Language :: Python
